README
setup.py
PyReadability.egg-info/PKG-INFO
PyReadability.egg-info/SOURCES.txt
PyReadability.egg-info/dependency_links.txt
PyReadability.egg-info/requires.txt
PyReadability.egg-info/top_level.txt
readability/__init__.py
readability/cleaners.py
readability/debug.py
readability/encoding.py
readability/htmls.py
readability/readability.py