Metadata-Version: 1.1
Name: PyReadability
Version: 0.4.0
Summary: fast python port of arc90's readability tool
Home-page: http://github.com/hyperlinkapp/python-readability
Author: Yuri Baburov
Author-email: burchik@gmail.com
License: Apache License 2.0
Platform: UNKNOWN
Classifier: Environment :: Web Environment
Classifier: Intended Audience :: Developers
Classifier: Operating System :: OS Independent
Classifier: Programming Language :: Python
